googlefonts_installer.py
googlefonts_installer-0.3.1.dist-info/DESCRIPTION.rst
googlefonts_installer-0.3.1.dist-info/METADATA
googlefonts_installer-0.3.1.dist-info/RECORD
googlefonts_installer-0.3.1.dist-info/WHEEL
googlefonts_installer-0.3.1.dist-info/entry_points.txt
googlefonts_installer-0.3.1.dist-info/metadata.json
googlefonts_installer-0.3.1.dist-info/top_level.txt
