Metadata-Version: 1.1
Name: googlefonts_installer
Version: 0.3.1
Summary: Google fonts installer utility.
Home-page: https://github.com/fabianbuechler/googlefonts_installer
Author: Fabian Büchler
Author-email: fabian@buechler.io
License: MIT
Platform: UNKNOWN
Classifier: Development Status :: 3 - Alpha
Classifier: Environment :: Console
Classifier: Intended Audience :: End Users/Desktop
Classifier: License :: OSI Approved :: MIT License
Classifier: Operating System :: POSIX :: Linux
Classifier: Programming Language :: Python :: 3
Classifier: Topic :: Text Processing :: Fonts
